merakicat/__init__.py
merakicat/bulk_check.sh
merakicat/bulk_migrate.sh
merakicat/mc_cfg_check.py
merakicat/mc_claim.py
merakicat/mc_cloud_mon.py
merakicat/mc_file_exists.py
merakicat/mc_get_config.py
merakicat/mc_get_nms.py
merakicat/mc_pedia.py
merakicat/mc_pedia2.py
merakicat/mc_ping.py
merakicat/mc_register.py
merakicat/mc_splitcheck_serials.py
merakicat/mc_translate.py
merakicat/mc_user_info.py
merakicat/merakicat.py
merakicat/test.txt
merakicat/test_script.sh
merakicat/batch_helper/__init__.py
merakicat/batch_helper/config.py
merakicat/batch_helper/exceptions.py
merakicat-1.0.1.dist-info/licenses/AUTHORS.rst
merakicat-1.0.1.dist-info/licenses/LICENSE
merakicat-1.0.1.dist-info/METADATA
merakicat-1.0.1.dist-info/WHEEL
merakicat-1.0.1.dist-info/top_level.txt
merakicat-1.0.1.dist-info/RECORD
