Metadata-Version: 2.4
Name: merakicat
Version: 1.0.1
Summary: An app to check and translate Catalyst switch configs to Meraki.
Home-page: https://github.com/ecoen66/merakicat
Author: Ed Coen
Author-email: ecoen@cisco.com
License: MIT license
Keywords: merakicat,catalyst,meraki,cisco,migration,webexteamsbot
Classifier: Development Status :: 2 - Pre-Alpha
Classifier: Intended Audience :: Developers
Classifier: License :: OSI Approved :: MIT License
Classifier: Natural Language :: English
Classifier: Programming Language :: Python :: 3.10
Classifier: Programming Language :: Python :: 3.11
Classifier: Programming Language :: Python :: 3 :: Only
License-File: LICENSE
License-File: AUTHORS.rst
Requires-Dist: webex-bot==0.4.7
Requires-Dist: webexteamssdk==1.6.1
Requires-Dist: Flask>=0.12.1
Requires-Dist: netmiko==4.3.0
Requires-Dist: tabulate==0.9.0
Requires-Dist: ciscoconfparse2==0.7.50
Requires-Dist: meraki==1.46.0
Requires-Dist: python-docx==1.1.2
Requires-Dist: docx2pdf==0.1.8
Requires-Dist: requests==2.31.0
Dynamic: author
Dynamic: author-email
Dynamic: classifier
Dynamic: description
Dynamic: description-content-type
Dynamic: home-page
Dynamic: keywords
Dynamic: license
Dynamic: license-file
Dynamic: requires-dist
Dynamic: summary
